devinci_pyutils/__init__.py
devinci_pyutils/banner.py
devinci_pyutils/file_utils.py
devinci_pyutils/terminal.py
devinci_pyutils/writer.py
py_scaffold/__init__.py
py_scaffold/helpers.py
py_scaffold/main.py
py_scaffold/setup.py
py_scaffold/template_hydrator.py
devinci_pyutils-1.0.0.dist-info/METADATA
devinci_pyutils-1.0.0.dist-info/WHEEL
devinci_pyutils-1.0.0.dist-info/top_level.txt
devinci_pyutils-1.0.0.dist-info/RECORD
