Metadata-Version: 2.1
Name: devinci-pyutils
Version: 1.0.0
Summary: Collection of Python utility modules for developers.
Home-page: https://gist.github.com/devinci-it/d432708e796d6e6160efe13ee6cc7bbc/
Author: devinci-it
License: MIT
Requires-Python: >=3.6
